pylipid/__init__.py
pylipid/_version.py
pylipid/api/__init__.py
pylipid/api/api.py
pylipid/func/__init__.py
pylipid/func/binding_site.py
pylipid/func/clusterer.py
pylipid/func/interactions.py
pylipid/func/kinetics.py
pylipid/plot/__init__.py
pylipid/plot/koff.py
pylipid/plot/plot1d.py
pylipid/plot/plot2d.py
pylipid/util/__init__.py
pylipid/util/coordinate.py
pylipid/util/corrcoef.py
pylipid/util/directory.py
pylipid/util/pymol_script.py
pylipid/util/rmsd.py
pylipid/util/trajectory.py
pylipid-1.5.14.dist-info/LICENSE.txt
pylipid-1.5.14.dist-info/METADATA
pylipid-1.5.14.dist-info/WHEEL
pylipid-1.5.14.dist-info/top_level.txt
pylipid-1.5.14.dist-info/RECORD
