Metadata-Version: 2.1
Name: pylipid
Version: 1.5.14
Summary: PyLipID - A Python Library For Lipid Interaction Analysis
Home-page: https://github.com/wlsong/PyLipID
Author: Wanling Song
Author-email: wanling.song@hotmail.com
License: UNKNOWN
Keywords: simulation tools,network community,binding site
Platform: UNKNOWN
Classifier: Development Status :: 5 - Production/Stable
Classifier: Intended Audience :: Science/Research
Classifier: Topic :: Scientific/Engineering :: Bio-Informatics
Classifier: Topic :: Scientific/Engineering :: Chemistry
Classifier: Topic :: Scientific/Engineering :: Mathematics
Classifier: Topic :: Scientific/Engineering :: Physics
Classifier: License :: OSI Approved :: MIT License
Classifier: Programming Language :: Python :: 3.6
Classifier: Programming Language :: Python :: 3.7
Classifier: Programming Language :: Python :: 3.8
Requires-Python: >=3.6, <4, !=3.8.*
Requires-Dist: mdtraj
Requires-Dist: numpy
Requires-Dist: pandas
Requires-Dist: matplotlib (>=3.3.3)
Requires-Dist: networkx
Requires-Dist: scipy
Requires-Dist: python-louvain
Requires-Dist: logomaker
Requires-Dist: statsmodels
Requires-Dist: scikit-learn
Requires-Dist: tqdm
Requires-Dist: p-tqdm
Requires-Dist: kneebow
